LICENSE
README.md
setup.py
CVE_2020_3452.egg-info/PKG-INFO
CVE_2020_3452.egg-info/SOURCES.txt
CVE_2020_3452.egg-info/dependency_links.txt
CVE_2020_3452.egg-info/entry_points.txt
CVE_2020_3452.egg-info/requires.txt
CVE_2020_3452.egg-info/top_level.txt
cve20203452/__init__.py
cve20203452/main.py
cve20203452/includes/__init__.py
cve20203452/includes/bot.py
cve20203452/includes/filereader.py
cve20203452/includes/scan.py
cve20203452/includes/writefile.py
cve20203452/utils/__init__.py
cve20203452/utils/configure.py
cve20203452/utils/const.py
cve20203452/utils/helpers.py
cve20203452/utils/status.py